parallax/__init__.py
parallax/__main__.py
parallax/main_window.py
parallax/model.py
parallax/cameras/__init__.py
parallax/cameras/calibration_camera.py
parallax/cameras/camera.py
parallax/cameras/camera_base_binding.py
parallax/config/__init__.py
parallax/config/cli.py
parallax/config/config_calibration.py
parallax/config/config_path.py
parallax/config/image_processing_config.json
parallax/config/user_setting_manager.py
parallax/control_panel/control_panel.py
parallax/control_panel/probe_calibration_handler.py
parallax/control_panel/reticle_detect_handler.py
parallax/control_panel/stereo_camera_handler.py
parallax/control_panel/transform_info_handler.py
parallax/handlers/__init__.py
parallax/handlers/calculator.py
parallax/handlers/point_mesh.py
parallax/handlers/recording_manager.py
parallax/handlers/reticle_metadata.py
parallax/handlers/screen_coords_mapper.py
parallax/probe_calibration/__init__.py
parallax/probe_calibration/bundle_adjustment.py
parallax/probe_calibration/probe_calibration.py
parallax/probe_detection/__init__.py
parallax/probe_detection/opencv_process_worker.py
parallax/probe_detection/probe_detect_manager.py
parallax/probe_detection/yolo_process_worker.py
parallax/probe_detection/opencv/__init__.py
parallax/probe_detection/opencv/curr_bg_cmp_processor.py
parallax/probe_detection/opencv/curr_prev_cmp_processor.py
parallax/probe_detection/opencv/probe_detector.py
parallax/probe_detection/utils/__init__.py
parallax/probe_detection/utils/probe_fine_tip_detector.py
parallax/probe_detection/utils/probe_img_processor.py
parallax/probe_detection/utils/probe_spin_detector.py
parallax/probe_detection/yolo_global/__init__.py
parallax/probe_detection/yolo_global/utils.py
parallax/probe_detection/yolo_global/yolo_client.py
parallax/probe_detection/yolo_global/yolo_server.py
parallax/probe_detection/yolo_local/__init__.py
parallax/probe_detection/yolo_local/utils.py
parallax/probe_detection/yolo_local/yolo_client.py
parallax_app-1.15.1.dist-info/licenses/LICENSE
parallax_app-1.15.1.dist-info/METADATA
parallax_app-1.15.1.dist-info/WHEEL
parallax_app-1.15.1.dist-info/top_level.txt
parallax_app-1.15.1.dist-info/RECORD
