Metadata-Version: 2.4
Name: parallax-app
Version: 1.15.1
Summary: GUI software for photogrammetry-assisted probe targeting in electrophysiology
Author-email: Hanna Lee <hanna.lee@alleninstitute.org>
License: MIT
Keywords: parallax
Classifier: Programming Language :: Python :: 3
Requires-Python: ~=3.10
License-File: LICENSE
Requires-Dist: pip
Requires-Dist: PyQt6>=6.10.0
Requires-Dist: pyqtgraph
Requires-Dist: opencv-python
Requires-Dist: scipy
Requires-Dist: pandas
Requires-Dist: scikit-image
Requires-Dist: requests
Requires-Dist: scikit-learn
Requires-Dist: plotly
Requires-Dist: PyQt6-WebEngine>=6.10.0
Requires-Dist: aiohttp
Requires-Dist: pyyaml
Requires-Dist: SimpleITK
Requires-Dist: ultralytics>=8.2.0
Requires-Dist: torch>=2.3.0
Provides-Extra: dev
Requires-Dist: parallax-app[linters]; extra == "dev"
Provides-Extra: linters
Requires-Dist: codespell; extra == "linters"
Requires-Dist: coverage; extra == "linters"
Requires-Dist: flake8; extra == "linters"
Requires-Dist: interrogate; extra == "linters"
Requires-Dist: isort; extra == "linters"
Requires-Dist: pytest-mock; extra == "linters"
Provides-Extra: docs
Requires-Dist: Sphinx; extra == "docs"
Requires-Dist: sphinxcontrib-video; extra == "docs"
Requires-Dist: sphinx-jinja; extra == "docs"
Requires-Dist: furo; extra == "docs"
Requires-Dist: docutils; extra == "docs"
Provides-Extra: test
Requires-Dist: pytest>=7; extra == "test"
Requires-Dist: pytest-qt>=4.4.0; extra == "test"
Requires-Dist: pytest-cov>=4.1.0; extra == "test"
Requires-Dist: pytest-mock>=3.10.0; extra == "test"
Requires-Dist: opencv-python-headless; extra == "test"
Dynamic: license-file
